{
  "catalogueId": "pickupPortal",
  "catalogueName": "Church Pickup Requests",
  "currency": "INR",
  "publishedAt": "2026-05-04T23:28:18.851Z",
  "generatedAt": "2026-05-04T23:28:18.851Z",
  "version": 2,
  "pickupNotice": "Submit a pickup request and wait for confirmation from the church store team before collection.",
  "pickupLocation": "Church Resource Centre",
  "contactPhone": "24242334",
  "requestLeadTimeHours": 24,
  "categories": [
    {
      "id": "XmPVxsnTU3TxbMxd4jbd",
      "name": "Dates & Carrot - Cake"
    }
  ],
  "items": [
    {
      "id": "TVcy8QbGMQOxLmGUTP0n__tUPMrnoiBeBI3XRd0iFu",
      "sourceCatalogueId": "TVcy8QbGMQOxLmGUTP0n",
      "sourceCatalogueName": "2026 Christmas - Sales",
      "sourceCatalogueItemId": "tUPMrnoiBeBI3XRd0iFu",
      "productId": "wDu2v1zVzAqW1gNO69L3",
      "itemId": "ITEM-1777795780315",
      "name": "Dates & Carrot Cake (250 grams)",
      "categoryId": "XmPVxsnTU3TxbMxd4jbd",
      "categoryName": "Dates & Carrot - Cake",
      "description": "",
      "price": 1268.56,
      "unitLabel": "each",
      "imageLabel": "D&",
      "isAvailable": true
    }
  ]
}
